rox_icu/__init__.py
rox_icu/bit_ops.py
rox_icu/can_protocol.py
rox_icu/can_utils.py
rox_icu/cli.py
rox_icu/core.py
rox_icu/mock.py
rox_icu/monitor.py
rox_icu/py.typed
rox_icu/utils.py
rox_icu/version.py
rox_icu/dbc/__init__.py
rox_icu/dbc/rox_icu.dbc
rox_icu/examples/__init__.py
rox_icu/examples/wait_and_toggle.py
rox_icu/firmware/README.md
rox_icu/firmware/__init__.py
rox_icu/firmware/mocks/__init__.py
rox_icu/firmware/mocks/canio.py
rox_icu/firmware/mocks/digitalio.py
rox_icu/firmware/mocks/gc.py
rox_icu/firmware/mocks/icu_board.py
rox_icu/firmware/mocks/micropython.py
rox_icu/firmware/remote_io/__init__.py
rox_icu/firmware/remote_io/main.py
rox_icu-2.5.1.dist-info/LICENSE
rox_icu-2.5.1.dist-info/METADATA
rox_icu-2.5.1.dist-info/WHEEL
rox_icu-2.5.1.dist-info/entry_points.txt
rox_icu-2.5.1.dist-info/top_level.txt
rox_icu-2.5.1.dist-info/RECORD
