Metadata-Version: 2.2
Name: rox-icu
Version: 2.5.1
Summary: Integrated control unit
Author-email: ROX Automation <jev@roxautomation.com>
License: MIT
Project-URL: Homepage, https://github.com/rox-automation/rox-icu
Classifier: Development Status :: 3 - Alpha
Classifier: Intended Audience :: Developers
Classifier: Operating System :: OS Independent
Classifier: Programming Language :: Python
Classifier: Programming Language :: Python :: 3.11
Classifier: Topic :: Software Development :: Libraries :: Python Modules
Classifier: Typing :: Typed
Requires-Python: >=3.11
License-File: LICENSE
Requires-Dist: aiomqtt
Requires-Dist: candbg
Requires-Dist: click
Requires-Dist: coloredlogs
Requires-Dist: orjson
Requires-Dist: python-can
Provides-Extra: dev
